LICENSE
MANIFEST.in
README.rst
changelog
requirements.txt
setup.py
idnits/__init__.py
idnits/checks.py
idnits/parser.py
idnits/run.py
idnits/tests.py
idnits/utils.py
idnits.egg-info/PKG-INFO
idnits.egg-info/SOURCES.txt
idnits.egg-info/dependency_links.txt
idnits.egg-info/entry_points.txt
idnits.egg-info/not-zip-safe
idnits.egg-info/requires.txt
idnits.egg-info/top_level.txt