Metadata-Version: 2.1
Name: idnits
Version: 3.0.0
Summary: Convert text-format RFCs and Internet-Drafts to .xml format
Home-page: https://tools.ietf.org/tools/ietfdb/browser/branch/elft/idnits/
Author: Henrik Levkowetz
Author-email: henrik@levkowetz.com
License: Simplified BSD
Keywords: Internet-Draft text to xml conversion
Platform: UNKNOWN
Classifier: Development Status :: 5 - Production/Stable
Classifier: Intended Audience :: Other Audience
Classifier: Topic :: Text Processing
Classifier: Topic :: Text Processing :: Markup :: XML
Classifier: License :: OSI Approved :: BSD License
Classifier: Programming Language :: Python :: 2
Classifier: Programming Language :: Python :: 2.7
Provides-Extra: dev
